{"is_source_file": true, "format": "TypeScript", "description": "This file defines the routing endpoints for order-related operations in an Express.js backend, including placing an order and retrieving user-specific order history. It imports middleware for authentication and validation, references controller functions, and includes Swagger documentation comments.", "external_files": ["../../middleware/auth", "../../middleware/validate", "./orders.controller", "./orders.schemas"], "external_methods": ["requireAuth", "validate", "controller.place", "controller.myOrders"], "published": ["router"], "classes": [], "methods": [{"name": "router.post", "description": "Defines the POST endpoint for creating a new order that requires authentication and request validation."}, {"name": "router.get", "description": "Defines the GET endpoint for fetching order history of the current user, requiring authentication."}], "calls": ["requireAuth", "validate", "controller.place", "controller.myOrders"], "search-terms": ["orders.routes", "placeOrderSchema", "Express router", "Order endpoints", "Order API", "Order controller"], "state": 2, "file_id": 30, "knowledge_revision": 72, "git_revision": "acdf6c5f71c0ea8b20a8614e60589a49d7717633", "ctags": [{"_type": "tag", "name": "router", "path": "/home/kavia/workspace/code-generation/e-commerce-backend-system-302508-302517/backend_api/src/modules/orders/orders.routes.ts", "pattern": "/^const router = Router();$/", "language": "TypeScript", "kind": "constant"}], "hash": "7610d5d4bf459c7a49814b83c8127cf7", "format-version": 4, "code-base-name": "backend_api", "filename": "backend_api/src/modules/orders/orders.routes.ts", "revision_history": [{"72": "acdf6c5f71c0ea8b20a8614e60589a49d7717633"}]}